thoughtcli/__init__.py
thoughtcli/connection.py
thoughtcli-0.3.0.dist-info/METADATA
thoughtcli-0.3.0.dist-info/WHEEL
thoughtcli-0.3.0.dist-info/entry_points.txt
thoughtcli-0.3.0.dist-info/top_level.txt
thoughtcli-0.3.0.dist-info/RECORD
